dual_quaternions/__init__.py
dual_quaternions/dual_quaternions.py
dual_quaternions-0.4.0.dist-info/licenses/LICENSE
dual_quaternions-0.4.0.dist-info/METADATA
dual_quaternions-0.4.0.dist-info/WHEEL
dual_quaternions-0.4.0.dist-info/top_level.txt
dual_quaternions-0.4.0.dist-info/RECORD
