Metadata-Version: 2.4
Name: dual_quaternions
Version: 0.4.0
Summary: Dual quaternion implementation
Home-page: http://github.com/Achllle/dual_quaternions
Author: Achille Verheye
Author-email: achille.verheye@gmail.com
License: MIT
License-File: LICENSE
Requires-Dist: numpy
Requires-Dist: pyquaternion
Dynamic: author
Dynamic: author-email
Dynamic: description
Dynamic: description-content-type
Dynamic: home-page
Dynamic: license
Dynamic: license-file
Dynamic: requires-dist
Dynamic: summary
